insql/__init__.py
insql/core.py
insql-1.0.0.dist-info/LICENCE
insql-1.0.0.dist-info/METADATA
insql-1.0.0.dist-info/WHEEL
insql-1.0.0.dist-info/top_level.txt
insql-1.0.0.dist-info/RECORD
