Metadata-Version: 2.1
Name: insql
Version: 1.0.0
Summary: A lightweight SQL-like database library for Python
Home-page: UNKNOWN
Author: flamecode
License: MIT
Project-URL: Documentation, https://intealdev.github.io/InSQL-Documentation/
Keywords: database sql lightweight embedded
Platform: UNKNOWN
Classifier: Development Status :: 4 - Beta
Classifier: Intended Audience :: Developers
Classifier: License :: OSI Approved :: MIT License
Classifier: Programming Language :: Python :: 3
Classifier: Programming Language :: Python :: 3.6
Classifier: Programming Language :: Python :: 3.7
Classifier: Programming Language :: Python :: 3.8
Classifier: Programming Language :: Python :: 3.9
Classifier: Programming Language :: Python :: 3.10
Classifier: Operating System :: OS Independent
Classifier: Topic :: Database
Classifier: Topic :: Software Development :: Libraries :: Python Modules
Requires-Python: >=3.6
